
{
  "Human Digestive Energy Balance" : {
            "Energy-balance-0" : "Energy Balance 0",
            "Energy-balance-1" : "Energy Balance 1",
            "Energy-balance-2" : "Energy Balance 2",
            "Energy-balance-3" : "Energy Balance 3",
            "Energy-balance-4" : "Energy Balance 4",
            "Energy-balance-5" : "Energy Balance 5",
            "Energy-balance-6" : "Energy Balance 6",
            "Energy-balance-7" : "Energy Balance 7",
            "Energy-balance-8" : "Energy Balance 8"
        },

        "Blood Glucose" : {
            "zero-set-point-homeostasis" : "Zero set point homeostasis",
            "nonzero-set-point-homeostasis" : "Nonzero set point homeostasis",
            "two-loop-homoestatis":"Two loop homoestatis",
            "simple-Blood-glucose homoestatis" : "Simple Blood glucose homoestatis" ,
            "glucose-min-model" : "Glucose min model"
        },

        "Mastering model construction: Problem Set 1":{
            "CPI-2014-ps1-01" :"MMC Problem 1.01",
            "CPI-2014-ps1-02" :"MMC Problem 1.02",
            "CPI-2014-ps1-03" :"MMC Problem 1.03",
            "CPI-2014-ps1-04" :"MMC Problem 1.04",
            "CPI-2014-ps1-05" :"MMC Problem 1.05",
            "CPI-2014-ps1-06" :"MMC Problem 1.06",
            "CPI-2014-ps1-07" :"MMC Problem 1.07",
            "CPI-2014-ps1-08" :"MMC Problem 1.08",
            "CPI-2014-ps1-09" :"MMC Problem 1.09",
            "CPI-2014-ps1-10" :"MMC Problem 1.10",
            "CPI-2014-ps1-11" :"MMC Problem 1.11",
            "CPI-2014-ps1-12" :"MMC Problem 1.12"
        },

        "Mastering model construction: Problem Set 2":{
           "CPI-2014-ps2-01" :"MMC Problem 2.1",
           "CPI-2014-ps2-02" :"MMC Problem 2.2",
           "CPI-2014-ps2-03" :"MMC Problem 2.3",
           "CPI-2014-ps2-04" :"MMC Problem 2.4",
           "CPI-2014-ps2-05" :"MMC Problem 2.5",
           "CPI-2014-ps2-06" :"MMC Problem 2.6",
           "CPI-2014-ps2-07" :"MMC Problem 2.7",
           "CPI-2014-ps2-08" :"MMC Problem 2.8",
           "CPI-2014-ps2-09" :"MMC Problem 2.9"
        },

        "Mastering model construction: Problem Set 3":{
           "CPI-2014-ps3-01" :"MMC Problem 3.1",
           "CPI-2014-ps3-02" :"MMC Problem 3.2",
           "CPI-2014-ps3-03" :"MMC Problem 3.3",
           "CPI-2014-ps3-04" :"MMC Problem 3.4",
           "CPI-2014-ps3-05" :"MMC Problem 3.5",
           "CPI-2014-ps3-06" :"MMC Problem 3.6",
           "CPI-2014-ps3-07" :"MMC Problem 3.7",
           "CPI-2014-ps3-08" :"MMC Problem 3.8"
        },

        "Mastering model construction: Problem Set 4":{
           "CPI-2014-ps4-01" :"MMC Problem 4.1",
           "CPI-2014-ps4-02" :"MMC Problem 4.2",
           "CPI-2014-ps4-03" :"MMC Problem 4.3",
           "CPI-2014-ps4-04" :"MMC Problem 4.4",
           "CPI-2014-ps4-05" :"MMC Problem 4.5",
           "CPI-2014-ps4-06" :"MMC Problem 4.6"
        },

        "Mastering model construction: Problem Set 5":{
           "CPI-2014-ps5-01" :"MMC Problem 5.1",
           "CPI-2014-ps5-02" :"MMC Problem 5.2",
           "CPI-2014-ps5-03" :"MMC Problem 5.3",
           "CPI-2014-ps5-04" :"MMC Problem 5.4",
           "CPI-2014-ps5-05" :"MMC Problem 5.5",
           "CPI-2014-ps5-06" :"MMC Problem 5.6"
   },
        "Ecosystem Population Dynamics":{
            "isle1" : "Moose population 1",
            "isle2" : "Moose population 2",
            "isle3" : "Moose population 3",
            "isle4" : "Moose population 4",
            "isle5" : "Wolves",
            "isle6" : "Moose and Wolves",
            "201" : "Waterfowl 1",
            "202" : "Waterfowl 2",
            "203" : "Waterfowl 3",
            "204" : "Waterfowl & cats"
   },
        "Miscellaneous":{
            "real-giardia": "Real Giardia",
            "jared1" : "Jared's weight",
            "jared2" : "Jared Oprah",
            "jared3" : "Jared Oprah +",
            "jared4" : "Jared Oprah *",
            "dodos" : "Dodo extinction",
            "rabbits" : "Rabbit population",              
            "105":"Intro problem 1",
            "106":"Intro problem 2",
            "107":"Intro problem 3",
            "108":"Intro problem 4",
            "74":"Dying orchard",
            "92":"Bilge water",
            "94":"Rust",
            "110":"Chestnut blight",
            "95":"Bus Fleet",
            "93":"Rider gap",
            "96":"Capacity utilization",
            "97":"Bank Account",
            "98":"Merchant Marine",
            "80":"Metro Singles Club", 
            "111":"Bookworm",
            "99":"Venice",
            "109":"Giardia",
            "112":"Blood Glucose",
            "100":"Oil Tanker",
            "79":"Hardwood Forest",
            "101":"ASU Commuters",
            "115":"Widget Stocking",
            "113":"Busy Hospital",
            "114":"ObscureFlix"
       },
   
        "Kinematics": {
            "Fall-from-building-1" : "Fall from building 1",
            "Fall-from-building-2" : "Fall from building 2",
            "Fall-from-building-3" : "Fall from building 3",
            "Thrown-Stone-1" : "Thrown Stone 1",
            "Thrown-Stone-2" : "Thrown Stone 2"
        },

    "Generic Models":{
            "constant":"constant",
            "constant-change-runs-out":"constant change runs out",
            "propor-to-set-point-minus-destination":"propor to set point minus destination",
            "propor-to-source-minus-destination":"propor to source minus destination",
            "proportional-to-source":"proportional to source",
            "proportional-to-destination":"proportional to destination",
            "acceleration":"acceleration",
            "epidemic2":"epidemic2"
        }

    }
	     
